librasa/__init__.py
librasa/lab1.py
librasa/lab2.py
librasa/lab4.py
librasa/lab6.py
librasa/lab7.py
librasa/quiz1.py
librasa/utils.py
librasa-1.0.1.dist-info/licenses/LICENSE
librasa-1.0.1.dist-info/METADATA
librasa-1.0.1.dist-info/WHEEL
librasa-1.0.1.dist-info/top_level.txt
librasa-1.0.1.dist-info/RECORD
